<annotation>
	<filename>201005053.jpg</filename>
	<size>
		<width>400</width>
		<height>300</height>
		<depth>3</depth>
	</size>
	<object>
		<name>aquarium</name>
		<bndbox>
			<xmin>1</xmin>
			<ymin>132</ymin>
			<xmax>174</xmax>
			<ymax>272</ymax>
		</bndbox>
	</object>
	<object>
		<name>bucket</name>
		<bndbox>
			<xmin>89</xmin>
			<ymin>173</ymin>
			<xmax>164</xmax>
			<ymax>276</ymax>
		</bndbox>
	</object>
	<object>
		<name>bucket</name>
		<bndbox>
			<xmin>156</xmin>
			<ymin>215</ymin>
			<xmax>208</xmax>
			<ymax>285</ymax>
		</bndbox>
	</object>
	<object>
		<name>bucket</name>
		<bndbox>
			<xmin>173</xmin>
			<ymin>173</ymin>
			<xmax>232</xmax>
			<ymax>266</ymax>
		</bndbox>
	</object>
	<object>
		<name>bucket</name>
		<bndbox>
			<xmin>173</xmin>
			<ymin>114</ymin>
			<xmax>247</xmax>
			<ymax>236</ymax>
		</bndbox>
	</object>
	<object>
		<name>bucket</name>
		<bndbox>
			<xmin>246</xmin>
			<ymin>145</ymin>
			<xmax>295</xmax>
			<ymax>220</ymax>
		</bndbox>
	</object>
	<object>
		<name>bucket</name>
		<bndbox>
			<xmin>270</xmin>
			<ymin>135</ymin>
			<xmax>308</xmax>
			<ymax>198</ymax>
		</bndbox>
	</object>
	<object>
		<name>bucket</name>
		<bndbox>
			<xmin>295</xmin>
			<ymin>132</ymin>
			<xmax>321</xmax>
			<ymax>181</ymax>
		</bndbox>
	</object>
	<object>
		<name>bucket</name>
		<bndbox>
			<xmin>303</xmin>
			<ymin>108</ymin>
			<xmax>331</xmax>
			<ymax>142</ymax>
		</bndbox>
	</object>
	<object>
		<name>box</name>
		<bndbox>
			<xmin>242</xmin>
			<ymin>204</ymin>
			<xmax>331</xmax>
			<ymax>255</ymax>
		</bndbox>
	</object>
</annotation>