<annotation>
	<filename>201209283.jpg</filename>
	<size>
		<width>307</width>
		<height>230</height>
		<depth>3</depth>
	</size>
	<object>
		<name>bowl</name>
		<bndbox>
			<xmin>56</xmin>
			<ymin>144</ymin>
			<xmax>112</xmax>
			<ymax>190</ymax>
		</bndbox>
	</object>
	<object>
		<name>bowl</name>
		<bndbox>
			<xmin>102</xmin>
			<ymin>177</ymin>
			<xmax>219</xmax>
			<ymax>230</ymax>
		</bndbox>
	</object>
	<object>
		<name>bottle</name>
		<bndbox>
			<xmin>176</xmin>
			<ymin>143</ymin>
			<xmax>206</xmax>
			<ymax>167</ymax>
		</bndbox>
	</object>
	<object>
		<name>bottle</name>
		<bndbox>
			<xmin>217</xmin>
			<ymin>78</ymin>
			<xmax>228</xmax>
			<ymax>106</ymax>
		</bndbox>
	</object>
	<object>
		<name>bottle</name>
		<bndbox>
			<xmin>202</xmin>
			<ymin>86</ymin>
			<xmax>219</xmax>
			<ymax>113</ymax>
		</bndbox>
	</object>
</annotation>